echoframe/__init__.py
echoframe-2.0.0.dist-info/licenses/LICENSE
echoframe-2.0.0.dist-info/METADATA
echoframe-2.0.0.dist-info/WHEEL
echoframe-2.0.0.dist-info/entry_points.txt
echoframe-2.0.0.dist-info/top_level.txt
echoframe-2.0.0.dist-info/RECORD
