Metadata-Version: 2.4
Name: echoframe
Version: 2.0.0
Summary: 一个完整的 OneBot-11 协议插件化机器人框架 - EchoFrame
Home-page: https://github.com/your-repo/echoframe
Author: EchoFrame Team
Author-email: 
License: MIT
Project-URL: Homepage, https://github.com/your-repo/echoframe
Project-URL: Documentation, https://github.com/your-repo/echoframe/blob/main/README.md
Project-URL: Repository, https://github.com/your-repo/echoframe
Project-URL: Issues, https://github.com/your-repo/echoframe/issues
Keywords: onebot,qq,bot,framework,plugin,echoframe
Classifier: Development Status :: 4 - Beta
Classifier: Intended Audience :: Developers
Classifier: Topic :: Communications :: Chat
Classifier: License :: OSI Approved :: MIT License
Classifier: Programming Language :: Python :: 3
Classifier: Programming Language :: Python :: 3.8
Classifier: Programming Language :: Python :: 3.9
Classifier: Programming Language :: Python :: 3.10
Classifier: Programming Language :: Python :: 3.11
Classifier: Programming Language :: Python :: 3.12
Classifier: Programming Language :: Python :: 3.13
Requires-Python: >=3.8
License-File: LICENSE
Requires-Dist: aiohttp>=3.8.0
Requires-Dist: websockets>=11.0
Requires-Dist: pyyaml>=6.0
Requires-Dist: pydantic>=2.0.0
Requires-Dist: loguru>=0.7.0
Provides-Extra: scheduler
Requires-Dist: apscheduler>=3.10.0; extra == "scheduler"
Provides-Extra: database
Requires-Dist: sqlalchemy>=2.0.0; extra == "database"
Requires-Dist: aiosqlite>=0.19.0; extra == "database"
Provides-Extra: all
Requires-Dist: apscheduler>=3.10.0; extra == "all"
Requires-Dist: sqlalchemy>=2.0.0; extra == "all"
Requires-Dist: aiosqlite>=0.19.0; extra == "all"
Provides-Extra: dev
Requires-Dist: pytest>=7.0.0; extra == "dev"
Requires-Dist: pytest-asyncio>=0.21.0; extra == "dev"
Requires-Dist: black>=23.0.0; extra == "dev"
Requires-Dist: mypy>=1.0.0; extra == "dev"
Dynamic: home-page
Dynamic: license-file
Dynamic: requires-python
